novelsave/__init__.py
novelsave/__main__.py
novelsave/client/__init__.py
novelsave/client/bots/__init__.py
novelsave/client/bots/discord/__init__.py
novelsave/client/bots/discord/bot.py
novelsave/client/bots/discord/checks.py
novelsave/client/bots/discord/config.py
novelsave/client/bots/discord/containers.py
novelsave/client/bots/discord/decorators.py
novelsave/client/bots/discord/endpoints/__init__.py
novelsave/client/bots/discord/endpoints/commands.py
novelsave/client/bots/discord/endpoints/download.py
novelsave/client/bots/discord/endpoints/search.py
novelsave/client/bots/discord/endpoints/session.py
novelsave/client/bots/discord/exceptions.py
novelsave/client/bots/discord/main.py
novelsave/client/bots/discord/mixins.py
novelsave/client/bots/discord/session/__init__.py
novelsave/client/bots/discord/session/fragment.py
novelsave/client/bots/discord/session/handler.py
novelsave/client/bots/discord/session/session.py
novelsave/client/bots/discord/session/session_helper.py
novelsave/client/bots/discord/utils.py
novelsave/client/cli/__init__.py
novelsave/client/cli/controllers/__init__.py
novelsave/client/cli/controllers/_novel.py
novelsave/client/cli/controllers/_package.py
novelsave/client/cli/controllers/_update.py
novelsave/client/cli/controllers/_url.py
novelsave/client/cli/events.py
novelsave/client/cli/groups/__init__.py
novelsave/client/cli/groups/_config.py
novelsave/client/cli/groups/_manage.py
novelsave/client/cli/groups/_novel.py
novelsave/client/cli/helpers/__init__.py
novelsave/client/cli/helpers/novel.py
novelsave/client/cli/helpers/source.py
novelsave/client/cli/main.py
novelsave/containers.py
novelsave/core/__init__.py
novelsave/core/dtos/__init__.py
novelsave/core/dtos/chapter_dto.py
novelsave/core/dtos/metadata_dto.py
novelsave/core/dtos/novel_dto.py
novelsave/core/dtos/volume_dto.py
novelsave/core/entities/__init__.py
novelsave/core/entities/base.py
novelsave/core/entities/constants.py
novelsave/core/entities/novel/__init__.py
novelsave-0.8.4.dist-info/entry_points.txt
novelsave-0.8.4.dist-info/LICENSE
novelsave-0.8.4.dist-info/WHEEL
novelsave-0.8.4.dist-info/METADATA
novelsave-0.8.4.dist-info/RECORD
