Metadata-Version: 2.1
Name: novelsave
Version: 0.8.4
Summary: This is a tool to download and convert novels from popular sites to e-books.
Home-page: https://github.com/mensch272/novelsave
License: Apache-2.0
Keywords: novel,lightnovel,scraper,epub,mobi
Author: Mensch272
Author-email: 47662901+mensch272@users.noreply.github.com
Maintainer: Mensch272
Maintainer-email: 47662901+mensch272@users.noreply.github.com
Requires-Python: >=3.8,<4.0
Classifier: Development Status :: 5 - Production/Stable
Classifier: Intended Audience :: End Users/Desktop
Classifier: License :: OSI Approved :: Apache Software License
Classifier: Natural Language :: English
Classifier: Programming Language :: Python :: 3
Classifier: Programming Language :: Python :: 3 :: Only
Classifier: Programming Language :: Python :: 3.10
Classifier: Programming Language :: Python :: 3.8
Classifier: Programming Language :: Python :: 3.9
Classifier: Topic :: Games/Entertainment
Provides-Extra: discord
Requires-Dist: EbookLib (>=0.17.1,<0.18.0)
Requires-Dist: Mako (>=1.1.5,<2.0.0)
Requires-Dist: SQLAlchemy (>=1.4.24,<2.0.0)
Requires-Dist: alembic (>=1.7.5,<2.0.0)
Requires-Dist: appdirs (>=1.4.4,<2.0.0)
Requires-Dist: beautifulsoup4 (>=4.10.0,<5.0.0)
Requires-Dist: browser-cookie3 (>=0.13.0,<0.14.0)
Requires-Dist: click (>=8.0.1,<9.0.0)
Requires-Dist: dependency-injector (>=4.37.0,<5.0.0)
Requires-Dist: loguru (>=0.6.0,<0.7.0)
Requires-Dist: lxml (>=4.6.5,<5.0.0)
Requires-Dist: nextcord (>=2.0.0-alpha.3,<3.0.0); extra == "discord"
Requires-Dist: novelsave-sources (>=0.3.2,<0.4.0)
Requires-Dist: python-dotenv (>=0.19.2,<0.20.0)
Requires-Dist: requests (>=2.26.0,<3.0.0)
Requires-Dist: tabulate (>=0.8.9,<0.9.0)
Requires-Dist: tqdm (>=4.62.3,<5.0.0)
Project-URL: Documentation, https://github.com/mensch272/novelsave/blob/master/README.md
Project-URL: Issue Tracker, https://github.com/mensch272/novelsave/issues
Project-URL: Repository, https://github.com/mensch272/novelsave
Project-URL: Source Code, https://github.com/mensch272/novelsave
